Workbook

Sheet Holerite
B2: Empresa | C2: INFOTECH JANDIRA LTDA | G2: Recibo de Pagamento de Salário
B3: CNPJ | C3: 137845290000153 | G3: Mês | H3: JANEIRO | J3: Ano | K3: 2019 | N3: DECLARO TER RECEBIDO A IMPORTÂNCIA LÍQUIDA DISCRIMINADA NESTE RECIBO | O3: ______/ ______/ ______ _____________________________________ | P3: DATA ASSINATURA DO FUNCIONÁRIO
B5: Código | C5: Nome de Funcionário | E5: CBO | F5: Cargo | G5: Local | H5: Dpto. | I5: Setor | J5: Seção | K5: FL.
B6: 552487 | C6: =VLOOKUP($B$6,Funcionários!$A$2:$C$19,2,FALSE) -> Luan Ricardo de Moraes | E6: =VLOOKUP($B$6,Funcionários!$A$2:$C$19,3,FALSE) -> 142335 | F6: =VLOOKUP($E$6,'Cargos e Vencimentos'!$A$2:$C$11,2,FALSE) -> Analista de marketing
B8: Cód. | C8: Descrição | E8: Referência | F8: Vencimentos | I8: Descontos
B10: 101 | C10: =VLOOKUP(B10,'Referências e Descontos'!$A$3:$B$5,2,0) -> Salário | E10: =VLOOKUP(B10,'Referências e Descontos'!$A$3:$C$3,3,0) -> 30d | F10: =VLOOKUP($E$6,'Cargos e Vencimentos'!$A$2:$C$11,3,0) -> 3150
B11: 973 | C11: =VLOOKUP(B11,'Referências e Descontos'!$A$3:$B$5,2,0) -> INSS | E11: =VLOOKUP($F$10,'Referências e Descontos'!$E$4:$G$6,3,1) -> 0.11 | I11: =$F$10*E11 -> 346.5
B12: 987 | C12: =VLOOKUP(B12,'Referências e Descontos'!$A$3:$B$5,2,0) -> IRPF | E12: =VLOOKUP($F$10,'Referências e Descontos'!$I$4:$L$8,3,1) -> 0.15 | I12: =(F10-I11)*E12 -> 420.525
F29: Total de Vencimentos | I29: Total de Desconto
F30: =SUM($F$10:$H$27) -> 3150 | I30: =SUM($I$11:$L$27) -> 767.025
F32: Valor Líquido | I32: =$F$30-$I$30 -> 2382.975
B35: Salário base | D35: Sal. Cont. INSS | E35: Base Cálc. FGTS | G35: FGTS do Mês | I35: Base Cálc. IRPF | K35: Faixa IRPF
B36: =F10 -> 3150 | D36: =F10 -> 3150 | E36: =F30 -> 3150 | G36: =E36*8% -> 252 | I36: =F10-I11 -> 2803.5 | K36: =VLOOKUP($B$36,'Referências e Descontos'!$I$4:$L$8,4,1) -> 2

Sheet Calendário
A1: ANO | B1: MÊS
A2: 2019 | B2: JANEIRO
A3: 2020 | B3: FEVEREIRO
A4: 2021 | B4: MARÇO
A5: 2022 | B5: ABRIL
A6: 2023 | B6: MAIO
A7: 2024 | B7: JUNHO
A8: 2025 | B8: JULHO
A9: 2026 | B9: AGOSTO
A10: 2027 | B10: SETEMBRO
A11: 2028 | B11: OUTUBRO
A12: 2029 | B12: NOVEMBRO
A13: 2030 | B13: DEZEMBRO

Sheet Funcionários
A1: CÓDIGO DO FUNCIONÁRIO | B1: NOME DO FUNCIONÁRIO | C1: CBO
A2: 105489 | B2: João Baptista de Antunes Neto | C2: 411010
A3: 615483 | B3: Pedro Paulo Araújo de Souza | C3: 142320
A4: 552487 | B4: Luan Ricardo de Moraes | C4: 142335
A5: 747254 | B5: Paula Marcelina Perez | C5: 422315
A6: 965487 | B6: Luciana Antunes Gomes | C6: 313215
A7: 201548 | B7: Meire Cordeiro de Almeira | C7: 411010
A8: 400457 | B8: Sampaio Olavo de Alburquerque | C8: 422315
A9: 901355 | B9: Melinda Gomes de Souza | C9: 318305
A10: 256703 | B10: Maria Cecília Santos | C10: 142105
A11: 611825 | B11: José Américo Silva | C11: 411010
A12: 316487 | B12: Thalita Antunes Rene | C12: 142335
A13: 501224 | B13: Claudia Sprana | C13: 422315
... A19: 221445 | B19: Heitor Henrique Gonçalves | C19: 123105

Sheet Cargos e Vencimentos
A1: CBO | B1: CARGOS | C1: VENCIMENTOS
A2: 411010 | B2: Assintente administativo | C2: 2567
A3: 142320 | B3: Gerente de vendas | C3: 3200
A4: 142335 | B4: Analista de marketing | C4: 3150
A5: 422315 | B5: Atendente de telemarketing | C5: 1490
A6: 313215 | B6: Auxiliar técnico de eletrônica | C6: 1800
A7: 411050 | B7: Desenhista técnico de eletrônica | C7: 2200
A8: 422345 | B8: Gerente administativo | C8: 3290
A9: 318305 | B9: Gerente comercial | C9: 4570
A10: 142105 | B10: Auxiliar de limpeza | C10: 1320
A11: 123105 | B11: Diretor administativo | C11: 11640

Sheet Referências e Descontos
A1: LEGENDA REFERÊNCIAS | E1: TABELA INSS | I1: TABELA IRPF
A2: Código | B2: Descrição | C2: Referência | E2: Salários | G2: % de Desconto | I2: Base de Cálculo | K2: Alíquota (%) | L2: Faixa IRPF
A3: 101 | B3: Salário | C3: 30d | E3: De | F3: Até | I3: De | J3: Até
A4: 973 | B4: INSS | E4: 0 | F4: 1751.81 | G4: 0.08 | I4: 0 | J4: 1903.98 | K4: 0 | L4: 0
A5: 987 | B5: IRPF | E5: 1751.82 | F5: 2919.72 | G5: 0.09 | I5: 1903.99 | J5: 2826.65 | K5: 0.075 | L5: 1
E6: 2919.73 | F6: 5839.45 | G6: 0.11 | I6: 2826.66 | J6: 3751.05 | K6: 0.15 | L6: 2
I7: 3751.06 | J7: 4664.68 | K7: 0.225 | L7: 3
I8: 4664.69 | K8: 0.275 | L8: 4
